<cacti>	
	<hash_0200182a6f422822682db3d3cbd896dae816a2>
		<name>HBase 20.2 - RegionServer</name>
		<graph_templates>hash_000018c8090a72590fbd322811f4de6bf61e54|hash_0000185b22eb8a97324cf0598db5607fb3bcfc|hash_0000189e929e2e55cf2df21be6176408070b34|hash_00001814d9e9287795603ee23f3bb6ab5993e2|hash_0000189794452f58f4f968ff6e9bff550a338b|hash_000018080f8e5b8333256f54d6f9754d8a7533|hash_000018023b11dee7ac9ce024b2b51862d41616|hash_000018615daa4d4206777b88a13e4768149965|hash_000018feb34a939aebdce29b2769157f178995</graph_templates>
		<data_queries></data_queries>
	</hash_0200182a6f422822682db3d3cbd896dae816a2>
	<hash_000018c8090a72590fbd322811f4de6bf61e54>
		<name>HBase 20.2 - RegionServer - StoreFiles</name>
		<graph>
			<t_title></t_title>
			<title>|host_description| HBase 20.2 - RegionServer - StoreFiles</title>
			<t_image_format_id></t_image_format_id>
			<image_format_id>1</image_format_id>
			<t_height></t_height>
			<height>120</height>
			<t_width></t_width>
			<width>500</width>
			<t_slope_mode></t_slope_mode>
			<slope_mode>on</slope_mode>
			<t_auto_scale></t_auto_scale>
			<auto_scale>on</auto_scale>
			<t_auto_scale_opts></t_auto_scale_opts>
			<auto_scale_opts>2</auto_scale_opts>
			<t_auto_scale_log></t_auto_scale_log>
			<auto_scale_log></auto_scale_log>
			<t_scale_log_units></t_scale_log_units>
			<scale_log_units></scale_log_units>
			<t_auto_scale_rigid></t_auto_scale_rigid>
			<auto_scale_rigid></auto_scale_rigid>
			<t_auto_padding></t_auto_padding>
			<auto_padding>on</auto_padding>
			<t_export></t_export>
			<export>on</export>
			<t_upper_limit></t_upper_limit>
			<upper_limit>100</upper_limit>
			<t_lower_limit></t_lower_limit>
			<lower_limit>0</lower_limit>
			<t_base_value></t_base_value>
			<base_value>1000</base_value>
			<t_unit_value></t_unit_value>
			<unit_value></unit_value>
			<t_unit_exponent_value></t_unit_exponent_value>
			<unit_exponent_value></unit_exponent_value>
			<t_vertical_label></t_vertical_label>
			<vertical_label></vertical_label>
		</graph>
		<items>
			<hash_100018a6e868084ed9ae13186706d0c5545feb>
				<task_item_id>hash_0800180ffd839156564e6446f6d802d1894a4c</task_item_id>
				<color_id>4444FF</color_id>
				<alpha>FF</alpha>
				<graph_type_id>7</graph_type_id>
				<consolidation_function_id>1</consolidation_function_id>
				<cdef_id>0</cdef_id>
				<value></value>
				<gprint_id>hash_060018e9c43831e54eca8069317a2ce8c6f751</gprint_id>
				<text_format>storeFiles</text_format>
				<hard_return></hard_return>
				<sequence>1</sequence>
			</hash_100018a6e868084ed9ae13186706d0c5545feb>
			<hash_10001843bead98701fe6c2337fda492b06c116>
				<task_item_id>hash_0800180ffd839156564e6446f6d802d1894a4c</task_item_id>
				<color_id>0</color_id>
				<alpha>FF</alpha>
				<graph_type_id>9</graph_type_id>
				<consolidation_function_id>4</consolidation_function_id>
				<cdef_id>0</cdef_id>
				<value></value>
				<gprint_id>hash_060018e9c43831e54eca8069317a2ce8c6f751</gprint_id>
				<text_format>Current:</text_format>
				<hard_return></hard_return>
				<sequence>2</sequence>
			</hash_10001843bead98701fe6c2337fda492b06c116>
			<hash_100018bef85423722da3bf8ccf01a4aa5feb21>
				<task_item_id>hash_0800180ffd839156564e6446f6d802d1894a4c</task_item_id>
				<color_id>0</color_id>
				<alpha>FF</alpha>
				<graph_type_id>9</graph_type_id>
				<consolidation_function_id>1</consolidation_function_id>
				<cdef_id>0</cdef_id>
				<value></value>
				<gprint_id>hash_060018e9c43831e54eca8069317a2ce8c6f751</gprint_id>
				<text_format>Average:</text_format>
				<hard_return></hard_return>
				<sequence>3</sequence>
			</hash_100018bef85423722da3bf8ccf01a4aa5feb21>
			<hash_100018d24e1b3019b856ec34f3558f59ec6f27>
				<task_item_id>hash_0800180ffd839156564e6446f6d802d1894a4c</task_item_id>
				<color_id>0</color_id>
				<alpha>FF</alpha>
				<graph_type_id>9</graph_type_id>
				<consolidation_function_id>3</consolidation_function_id>
				<cdef_id>0</cdef_id>
				<value></value>
				<gprint_id>hash_060018e9c43831e54eca8069317a2ce8c6f751</gprint_id>
				<text_format>Maximum:</text_format>
				<hard_return>on</hard_return>
				<sequence>4</sequence>
			</hash_100018d24e1b3019b856ec34f3558f59ec6f27>
		</items>
		<inputs>
			<hash_090018f714222f4e49826f4c52576aeac94a32>
				<name>Data Source [storefiles]</name>
				<description></description>
				<column_name>task_item_id</column_name>
				<items>hash_000018a6e868084ed9ae13186706d0c5545feb|hash_00001843bead98701fe6c2337fda492b06c116|hash_000018bef85423722da3bf8ccf01a4aa5feb21|hash_000018d24e1b3019b856ec34f3558f59ec6f27</items>
			</hash_090018f714222f4e49826f4c52576aeac94a32>
		</inputs>
	</hash_000018c8090a72590fbd322811f4de6bf61e54>
	<hash_0000185b22eb8a97324cf0598db5607fb3bcfc>
		<name>HBase 20.2 - RegionServer - Stores</name>
		<graph>
			<t_title></t_title>
			<title>|host_description| HBase 20.2 - RegionServer - Stores</title>
			<t_image_format_id></t_image_format_id>
			<image_format_id>1</image_format_id>
			<t_height></t_height>
			<height>120</height>
			<t_width></t_width>
			<width>500</width>
			<t_slope_mode></t_slope_mode>
			<slope_mode>on</slope_mode>
			<t_auto_scale></t_auto_scale>
			<auto_scale>on</auto_scale>
			<t_auto_scale_opts></t_auto_scale_opts>
			<auto_scale_opts>2</auto_scale_opts>
			<t_auto_scale_log></t_auto_scale_log>
			<auto_scale_log></auto_scale_log>
			<t_scale_log_units></t_scale_log_units>
			<scale_log_units></scale_log_units>
			<t_auto_scale_rigid></t_auto_scale_rigid>
			<auto_scale_rigid></auto_scale_rigid>
			<t_auto_padding></t_auto_padding>
			<auto_padding>on</auto_padding>
			<t_export></t_export>
			<export>on</export>
			<t_upper_limit></t_upper_limit>
			<upper_limit>100</upper_limit>
			<t_lower_limit></t_lower_limit>
			<lower_limit>0</lower_limit>
			<t_base_value></t_base_value>
			<base_value>1000</base_value>
			<t_unit_value></t_unit_value>
			<unit_value></unit_value>
			<t_unit_exponent_value></t_unit_exponent_value>
			<unit_exponent_value></unit_exponent_value>
			<t_vertical_label></t_vertical_label>
			<vertical_label></vertical_label>
		</graph>
		<items>
			<hash_100018b44ea0e7a0837dd3ed7a73b7d025a0f9>
				<task_item_id>hash_080018886eefbd178be1cc17b3ee37d906bb08</task_item_id>
				<color_id>4444FF</color_id>
				<alpha>FF</alpha>
				<graph_type_id>7</graph_type_id>
				<consolidation_function_id>1</consolidation_function_id>
				<cdef_id>0</cdef_id>
				<value></value>
				<gprint_id>hash_060018e9c43831e54eca8069317a2ce8c6f751</gprint_id>
				<text_format>stores</text_format>
				<hard_return></hard_return>
				<sequence>1</sequence>
			</hash_100018b44ea0e7a0837dd3ed7a73b7d025a0f9>
			<hash_10001857e20b3e1341bebb426d2f97a18a33ad>
				<task_item_id>hash_080018886eefbd178be1cc17b3ee37d906bb08</task_item_id>
				<color_id>0</color_id>
				<alpha>FF</alpha>
				<graph_type_id>9</graph_type_id>
				<consolidation_function_id>4</consolidation_function_id>
				<cdef_id>0</cdef_id>
				<value></value>
				<gprint_id>hash_060018e9c43831e54eca8069317a2ce8c6f751</gprint_id>
				<text_format>Current:</text_format>
				<hard_return></hard_return>
				<sequence>2</sequence>
			</hash_10001857e20b3e1341bebb426d2f97a18a33ad>
			<hash_10001856c5c6440b0502561d53e899ad6ee483>
				<task_item_id>hash_080018886eefbd178be1cc17b3ee37d906bb08</task_item_id>
				<color_id>0</color_id>
				<alpha>FF</alpha>
				<graph_type_id>9</graph_type_id>
				<consolidation_function_id>1</consolidation_function_id>
				<cdef_id>0</cdef_id>
				<value></value>
				<gprint_id>hash_060018e9c43831e54eca8069317a2ce8c6f751</gprint_id>
				<text_format>Average:</text_format>
				<hard_return></hard_return>
				<sequence>3</sequence>
			</hash_10001856c5c6440b0502561d53e899ad6ee483>
			<hash_100018ff2dd8457504739e8dafd301b42072fe>
				<task_item_id>hash_080018886eefbd178be1cc17b3ee37d906bb08</task_item_id>
				<color_id>0</color_id>
				<alpha>FF</alpha>
				<graph_type_id>9</graph_type_id>
				<consolidation_function_id>3</consolidation_function_id>
				<cdef_id>0</cdef_id>
				<value></value>
				<gprint_id>hash_060018e9c43831e54eca8069317a2ce8c6f751</gprint_id>
				<text_format>Maximum:</text_format>
				<hard_return>on</hard_return>
				<sequence>4</sequence>
			</hash_100018ff2dd8457504739e8dafd301b42072fe>
		</items>
		<inputs>
			<hash_090018c284cb5bce6d23a790c4e3b36652bf7a>
				<name>Data Source [stores]</name>
				<description></description>
				<column_name>task_item_id</column_name>
				<items>hash_000018b44ea0e7a0837dd3ed7a73b7d025a0f9|hash_00001857e20b3e1341bebb426d2f97a18a33ad|hash_00001856c5c6440b0502561d53e899ad6ee483|hash_000018ff2dd8457504739e8dafd301b42072fe</items>
			</hash_090018c284cb5bce6d23a790c4e3b36652bf7a>
		</inputs>
	</hash_0000185b22eb8a97324cf0598db5607fb3bcfc>
	<hash_0000189e929e2e55cf2df21be6176408070b34>
		<name>HBase 20.2 - RegionServer - Regions</name>
		<graph>
			<t_title></t_title>
			<title>|host_description| HBase 20.2 - RegionServer - Regions</title>
			<t_image_format_id></t_image_format_id>
			<image_format_id>1</image_format_id>
			<t_height></t_height>
			<height>120</height>
			<t_width></t_width>
			<width>500</width>
			<t_slope_mode></t_slope_mode>
			<slope_mode>on</slope_mode>
			<t_auto_scale></t_auto_scale>
			<auto_scale>on</auto_scale>
			<t_auto_scale_opts></t_auto_scale_opts>
			<auto_scale_opts>2</auto_scale_opts>
			<t_auto_scale_log></t_auto_scale_log>
			<auto_scale_log></auto_scale_log>
			<t_scale_log_units></t_scale_log_units>
			<scale_log_units></scale_log_units>
			<t_auto_scale_rigid></t_auto_scale_rigid>
			<auto_scale_rigid></auto_scale_rigid>
			<t_auto_padding></t_auto_padding>
			<auto_padding>on</auto_padding>
			<t_export></t_export>
			<export>on</export>
			<t_upper_limit></t_upper_limit>
			<upper_limit>100</upper_limit>
			<t_lower_limit></t_lower_limit>
			<lower_limit>0</lower_limit>
			<t_base_value></t_base_value>
			<base_value>1000</base_value>
			<t_unit_value></t_unit_value>
			<unit_value></unit_value>
			<t_unit_exponent_value></t_unit_exponent_value>
			<unit_exponent_value></unit_exponent_value>
			<t_vertical_label></t_vertical_label>
			<vertical_label></vertical_label>
		</graph>
		<items>
			<hash_1000180d6154d89b870daadbac0cbca4ed6dd6>
				<task_item_id>hash_080018dc0313937a701c83b6986ac43dfbb30f</task_item_id>
				<color_id>4444FF</color_id>
				<alpha>FF</alpha>
				<graph_type_id>7</graph_type_id>
				<consolidation_function_id>1</consolidation_function_id>
				<cdef_id>0</cdef_id>
				<value></value>
				<gprint_id>hash_060018e9c43831e54eca8069317a2ce8c6f751</gprint_id>
				<text_format>regions</text_format>
				<hard_return></hard_return>
				<sequence>1</sequence>
			</hash_1000180d6154d89b870daadbac0cbca4ed6dd6>
			<hash_1000181f9127355ebba96c5df10ddd88ed70fa>
				<task_item_id>hash_080018dc0313937a701c83b6986ac43dfbb30f</task_item_id>
				<color_id>0</color_id>
				<alpha>FF</alpha>
				<graph_type_id>9</graph_type_id>
				<consolidation_function_id>4</consolidation_function_id>
				<cdef_id>0</cdef_id>
				<value></value>
				<gprint_id>hash_060018e9c43831e54eca8069317a2ce8c6f751</gprint_id>
				<text_format>Current:</text_format>
				<hard_return></hard_return>
				<sequence>2</sequence>
			</hash_1000181f9127355ebba96c5df10ddd88ed70fa>
			<hash_1000187e4ff0b8b85bab17643d3ae1b31ee50b>
				<task_item_id>hash_080018dc0313937a701c83b6986ac43dfbb30f</task_item_id>
				<color_id>0</color_id>
				<alpha>FF</alpha>
				<graph_type_id>9</graph_type_id>
				<consolidation_function_id>1</consolidation_function_id>
				<cdef_id>0</cdef_id>
				<value></value>
				<gprint_id>hash_060018e9c43831e54eca8069317a2ce8c6f751</gprint_id>
				<text_format>Average:</text_format>
				<hard_return></hard_return>
				<sequence>3</sequence>
			</hash_1000187e4ff0b8b85bab17643d3ae1b31ee50b>
			<hash_1000183493405b8bcd12f19f1d615e3869b3ed>
				<task_item_id>hash_080018dc0313937a701c83b6986ac43dfbb30f</task_item_id>
				<color_id>0</color_id>
				<alpha>FF</alpha>
				<graph_type_id>9</graph_type_id>
				<consolidation_function_id>3</consolidation_function_id>
				<cdef_id>0</cdef_id>
				<value></value>
				<gprint_id>hash_060018e9c43831e54eca8069317a2ce8c6f751</gprint_id>
				<text_format>Maximum:</text_format>
				<hard_return>on</hard_return>
				<sequence>4</sequence>
			</hash_1000183493405b8bcd12f19f1d615e3869b3ed>
		</items>
		<inputs>
			<hash_090018eab3209741e0a159600578f25cc2513e>
				<name>Data Source [regions]</name>
				<description></description>
				<column_name>task_item_id</column_name>
				<items>hash_0000180d6154d89b870daadbac0cbca4ed6dd6|hash_0000181f9127355ebba96c5df10ddd88ed70fa|hash_0000187e4ff0b8b85bab17643d3ae1b31ee50b|hash_0000183493405b8bcd12f19f1d615e3869b3ed</items>
			</hash_090018eab3209741e0a159600578f25cc2513e>
		</inputs>
	</hash_0000189e929e2e55cf2df21be6176408070b34>
	<hash_00001814d9e9287795603ee23f3bb6ab5993e2>
		<name>HBase 20.2 - RegionServer - BlockCache</name>
		<graph>
			<t_title></t_title>
			<title>|host_description| HBase 20.2 - RegionServer - Stores</title>
			<t_image_format_id></t_image_format_id>
			<image_format_id>1</image_format_id>
			<t_height></t_height>
			<height>120</height>
			<t_width></t_width>
			<width>500</width>
			<t_slope_mode></t_slope_mode>
			<slope_mode>on</slope_mode>
			<t_auto_scale></t_auto_scale>
			<auto_scale>on</auto_scale>
			<t_auto_scale_opts></t_auto_scale_opts>
			<auto_scale_opts>2</auto_scale_opts>
			<t_auto_scale_log></t_auto_scale_log>
			<auto_scale_log></auto_scale_log>
			<t_scale_log_units></t_scale_log_units>
			<scale_log_units></scale_log_units>
			<t_auto_scale_rigid></t_auto_scale_rigid>
			<auto_scale_rigid></auto_scale_rigid>
			<t_auto_padding></t_auto_padding>
			<auto_padding>on</auto_padding>
			<t_export></t_export>
			<export>on</export>
			<t_upper_limit></t_upper_limit>
			<upper_limit>100</upper_limit>
			<t_lower_limit></t_lower_limit>
			<lower_limit>0</lower_limit>
			<t_base_value></t_base_value>
			<base_value>1000</base_value>
			<t_unit_value></t_unit_value>
			<unit_value></unit_value>
			<t_unit_exponent_value></t_unit_exponent_value>
			<unit_exponent_value></unit_exponent_value>
			<t_vertical_label></t_vertical_label>
			<vertical_label></vertical_label>
		</graph>
		<items>
			<hash_100018474676ab5ad1fe0f451bcc8b10bbe047>
				<task_item_id>hash_080018eb14139528c7814c4a9a55fd5727bf62</task_item_id>
				<color_id>FF0000</color_id>
				<alpha>FF</alpha>
				<graph_type_id>7</graph_type_id>
				<consolidation_function_id>1</consolidation_function_id>
				<cdef_id>0</cdef_id>
				<value></value>
				<gprint_id>hash_060018e9c43831e54eca8069317a2ce8c6f751</gprint_id>
				<text_format>blockCacheSize</text_format>
				<hard_return></hard_return>
				<sequence>1</sequence>
			</hash_100018474676ab5ad1fe0f451bcc8b10bbe047>
			<hash_100018da2de9db86815803774fdbaea4c43e7b>
				<task_item_id>hash_080018eb14139528c7814c4a9a55fd5727bf62</task_item_id>
				<color_id>0</color_id>
				<alpha>FF</alpha>
				<graph_type_id>9</graph_type_id>
				<consolidation_function_id>4</consolidation_function_id>
				<cdef_id>0</cdef_id>
				<value></value>
				<gprint_id>hash_060018e9c43831e54eca8069317a2ce8c6f751</gprint_id>
				<text_format>Current:</text_format>
				<hard_return></hard_return>
				<sequence>2</sequence>
			</hash_100018da2de9db86815803774fdbaea4c43e7b>
			<hash_1000189dc62a9bebe2a92b20f68d24f0dfd388>
				<task_item_id>hash_080018eb14139528c7814c4a9a55fd5727bf62</task_item_id>
				<color_id>0</color_id>
				<alpha>FF</alpha>
				<graph_type_id>9</graph_type_id>
				<consolidation_function_id>1</consolidation_function_id>
				<cdef_id>0</cdef_id>
				<value></value>
				<gprint_id>hash_060018e9c43831e54eca8069317a2ce8c6f751</gprint_id>
				<text_format>Average:</text_format>
				<hard_return></hard_return>
				<sequence>3</sequence>
			</hash_1000189dc62a9bebe2a92b20f68d24f0dfd388>
			<hash_100018f4102b5e541f2069fd2cb0d8d758f167>
				<task_item_id>hash_080018eb14139528c7814c4a9a55fd5727bf62</task_item_id>
				<color_id>0</color_id>
				<alpha>FF</alpha>
				<graph_type_id>9</graph_type_id>
				<consolidation_function_id>3</consolidation_function_id>
				<cdef_id>0</cdef_id>
				<value></value>
				<gprint_id>hash_060018e9c43831e54eca8069317a2ce8c6f751</gprint_id>
				<text_format>Maximum:</text_format>
				<hard_return>on</hard_return>
				<sequence>4</sequence>
			</hash_100018f4102b5e541f2069fd2cb0d8d758f167>
			<hash_1000183030bf379d8d891c9b65d31a211d2416>
				<task_item_id>hash_0800185ac598247dca64fdc2b09b75b7aee189</task_item_id>
				<color_id>4444FF</color_id>
				<alpha>FF</alpha>
				<graph_type_id>7</graph_type_id>
				<consolidation_function_id>1</consolidation_function_id>
				<cdef_id>0</cdef_id>
				<value></value>
				<gprint_id>hash_060018e9c43831e54eca8069317a2ce8c6f751</gprint_id>
				<text_format>blockCacheFree</text_format>
				<hard_return></hard_return>
				<sequence>5</sequence>
			</hash_1000183030bf379d8d891c9b65d31a211d2416>
			<hash_1000182f2800b086bd2babfdab9b689eceac44>
				<task_item_id>hash_0800185ac598247dca64fdc2b09b75b7aee189</task_item_id>
				<color_id>0</color_id>
				<alpha>FF</alpha>
				<graph_type_id>9</graph_type_id>
				<consolidation_function_id>4</consolidation_function_id>
				<cdef_id>0</cdef_id>
				<value></value>
				<gprint_id>hash_060018e9c43831e54eca8069317a2ce8c6f751</gprint_id>
				<text_format>Current:</text_format>
				<hard_return></hard_return>
				<sequence>6</sequence>
			</hash_1000182f2800b086bd2babfdab9b689eceac44>
			<hash_10001834ab9f56fb0eb7f2554c2f77a9218d36>
				<task_item_id>hash_0800185ac598247dca64fdc2b09b75b7aee189</task_item_id>
				<color_id>0</color_id>
				<alpha>FF</alpha>
				<graph_type_id>9</graph_type_id>
				<consolidation_function_id>1</consolidation_function_id>
				<cdef_id>0</cdef_id>
				<value></value>
				<gprint_id>hash_060018e9c43831e54eca8069317a2ce8c6f751</gprint_id>
				<text_format>Average:</text_format>
				<hard_return></hard_return>
				<sequence>7</sequence>
			</hash_10001834ab9f56fb0eb7f2554c2f77a9218d36>
			<hash_10001829b8ce70eb19a9509800e905b5d63f13>
				<task_item_id>hash_0800185ac598247dca64fdc2b09b75b7aee189</task_item_id>
				<color_id>0</color_id>
				<alpha>FF</alpha>
				<graph_type_id>9</graph_type_id>
				<consolidation_function_id>3</consolidation_function_id>
				<cdef_id>0</cdef_id>
				<value></value>
				<gprint_id>hash_060018e9c43831e54eca8069317a2ce8c6f751</gprint_id>
				<text_format>Maximum:</text_format>
				<hard_return>on</hard_return>
				<sequence>8</sequence>
			</hash_10001829b8ce70eb19a9509800e905b5d63f13>
		</items>
		<inputs>
			<hash_0900188b1c6f2bde9bbacc9fc4ebf480005343>
				<name>Data Source [blockCacheSize]</name>
				<description></description>
				<column_name>task_item_id</column_name>
				<items>hash_000018474676ab5ad1fe0f451bcc8b10bbe047|hash_000018da2de9db86815803774fdbaea4c43e7b|hash_0000189dc62a9bebe2a92b20f68d24f0dfd388|hash_000018f4102b5e541f2069fd2cb0d8d758f167</items>
			</hash_0900188b1c6f2bde9bbacc9fc4ebf480005343>
			<hash_0900188040ad30637c119afa6e2e04709ed556>
				<name>Data Source [blockCacheFree]</name>
				<description></description>
				<column_name>task_item_id</column_name>
				<items>hash_0000183030bf379d8d891c9b65d31a211d2416|hash_0000182f2800b086bd2babfdab9b689eceac44|hash_00001834ab9f56fb0eb7f2554c2f77a9218d36|hash_00001829b8ce70eb19a9509800e905b5d63f13</items>
			</hash_0900188040ad30637c119afa6e2e04709ed556>
		</inputs>
	</hash_00001814d9e9287795603ee23f3bb6ab5993e2>
	<hash_0000189794452f58f4f968ff6e9bff550a338b>
		<name>HBase 20.2 - RegionServer - BlockCache HitRatio</name>
		<graph>
			<t_title></t_title>
			<title>|host_description| HBase 20.2 - RegionServer - BlockCache hit Ratio</title>
			<t_image_format_id></t_image_format_id>
			<image_format_id>1</image_format_id>
			<t_height></t_height>
			<height>120</height>
			<t_width></t_width>
			<width>500</width>
			<t_slope_mode></t_slope_mode>
			<slope_mode>on</slope_mode>
			<t_auto_scale></t_auto_scale>
			<auto_scale>on</auto_scale>
			<t_auto_scale_opts></t_auto_scale_opts>
			<auto_scale_opts>2</auto_scale_opts>
			<t_auto_scale_log></t_auto_scale_log>
			<auto_scale_log></auto_scale_log>
			<t_scale_log_units></t_scale_log_units>
			<scale_log_units></scale_log_units>
			<t_auto_scale_rigid></t_auto_scale_rigid>
			<auto_scale_rigid></auto_scale_rigid>
			<t_auto_padding></t_auto_padding>
			<auto_padding>on</auto_padding>
			<t_export></t_export>
			<export>on</export>
			<t_upper_limit></t_upper_limit>
			<upper_limit>100</upper_limit>
			<t_lower_limit></t_lower_limit>
			<lower_limit>0</lower_limit>
			<t_base_value></t_base_value>
			<base_value>1000</base_value>
			<t_unit_value></t_unit_value>
			<unit_value></unit_value>
			<t_unit_exponent_value></t_unit_exponent_value>
			<unit_exponent_value></unit_exponent_value>
			<t_vertical_label></t_vertical_label>
			<vertical_label></vertical_label>
		</graph>
		<items>
			<hash_10001858290df6f36550add052c4875e1c0e13>
				<task_item_id>hash_080018605955075e17f25b7a4a601cc2cc5e5a</task_item_id>
				<color_id>4444FF</color_id>
				<alpha>FF</alpha>
				<graph_type_id>7</graph_type_id>
				<consolidation_function_id>1</consolidation_function_id>
				<cdef_id>0</cdef_id>
				<value></value>
				<gprint_id>hash_060018e9c43831e54eca8069317a2ce8c6f751</gprint_id>
				<text_format>blockCacheHitRatio</text_format>
				<hard_return></hard_return>
				<sequence>1</sequence>
			</hash_10001858290df6f36550add052c4875e1c0e13>
			<hash_100018e14c9c9c92eb046055dc18d433f7bf9a>
				<task_item_id>hash_080018605955075e17f25b7a4a601cc2cc5e5a</task_item_id>
				<color_id>0</color_id>
				<alpha>FF</alpha>
				<graph_type_id>9</graph_type_id>
				<consolidation_function_id>4</consolidation_function_id>
				<cdef_id>0</cdef_id>
				<value></value>
				<gprint_id>hash_060018e9c43831e54eca8069317a2ce8c6f751</gprint_id>
				<text_format>Current:</text_format>
				<hard_return></hard_return>
				<sequence>2</sequence>
			</hash_100018e14c9c9c92eb046055dc18d433f7bf9a>
			<hash_1000186328b4eaad7102bd70dab302d0977457>
				<task_item_id>hash_080018605955075e17f25b7a4a601cc2cc5e5a</task_item_id>
				<color_id>0</color_id>
				<alpha>FF</alpha>
				<graph_type_id>9</graph_type_id>
				<consolidation_function_id>1</consolidation_function_id>
				<cdef_id>0</cdef_id>
				<value></value>
				<gprint_id>hash_060018e9c43831e54eca8069317a2ce8c6f751</gprint_id>
				<text_format>Average:</text_format>
				<hard_return></hard_return>
				<sequence>3</sequence>
			</hash_1000186328b4eaad7102bd70dab302d0977457>
			<hash_10001823b94cd568e5c15b9e3c3d92425f284a>
				<task_item_id>hash_080018605955075e17f25b7a4a601cc2cc5e5a</task_item_id>
				<color_id>0</color_id>
				<alpha>FF</alpha>
				<graph_type_id>9</graph_type_id>
				<consolidation_function_id>3</consolidation_function_id>
				<cdef_id>0</cdef_id>
				<value></value>
				<gprint_id>hash_060018e9c43831e54eca8069317a2ce8c6f751</gprint_id>
				<text_format>Maximum:</text_format>
				<hard_return>on</hard_return>
				<sequence>4</sequence>
			</hash_10001823b94cd568e5c15b9e3c3d92425f284a>
		</items>
		<inputs>
			<hash_090018fa148c2b55613ac0b2cd5aaf6749f8e9>
				<name>Data Source [blockCacheHitRatio]</name>
				<description></description>
				<column_name>task_item_id</column_name>
				<items>hash_00001858290df6f36550add052c4875e1c0e13|hash_000018e14c9c9c92eb046055dc18d433f7bf9a|hash_0000186328b4eaad7102bd70dab302d0977457|hash_00001823b94cd568e5c15b9e3c3d92425f284a</items>
			</hash_090018fa148c2b55613ac0b2cd5aaf6749f8e9>
		</inputs>
	</hash_0000189794452f58f4f968ff6e9bff550a338b>
	<hash_000018080f8e5b8333256f54d6f9754d8a7533>
		<name>HBase 20.2 - RegionServer - BlockCache Count</name>
		<graph>
			<t_title></t_title>
			<title>|host_description| HBase 20.2 - RegionServer - BlockCache Count</title>
			<t_image_format_id></t_image_format_id>
			<image_format_id>1</image_format_id>
			<t_height></t_height>
			<height>120</height>
			<t_width></t_width>
			<width>500</width>
			<t_slope_mode></t_slope_mode>
			<slope_mode>on</slope_mode>
			<t_auto_scale></t_auto_scale>
			<auto_scale>on</auto_scale>
			<t_auto_scale_opts></t_auto_scale_opts>
			<auto_scale_opts>2</auto_scale_opts>
			<t_auto_scale_log></t_auto_scale_log>
			<auto_scale_log></auto_scale_log>
			<t_scale_log_units></t_scale_log_units>
			<scale_log_units></scale_log_units>
			<t_auto_scale_rigid></t_auto_scale_rigid>
			<auto_scale_rigid></auto_scale_rigid>
			<t_auto_padding></t_auto_padding>
			<auto_padding>on</auto_padding>
			<t_export></t_export>
			<export>on</export>
			<t_upper_limit></t_upper_limit>
			<upper_limit>100</upper_limit>
			<t_lower_limit></t_lower_limit>
			<lower_limit>0</lower_limit>
			<t_base_value></t_base_value>
			<base_value>1000</base_value>
			<t_unit_value></t_unit_value>
			<unit_value></unit_value>
			<t_unit_exponent_value></t_unit_exponent_value>
			<unit_exponent_value></unit_exponent_value>
			<t_vertical_label></t_vertical_label>
			<vertical_label></vertical_label>
		</graph>
		<items>
			<hash_1000184f19880945b8a1847f225c00603e9f5f>
				<task_item_id>hash_08001880aa850a079f23bd51d483bf5af8d670</task_item_id>
				<color_id>4444FF</color_id>
				<alpha>FF</alpha>
				<graph_type_id>7</graph_type_id>
				<consolidation_function_id>1</consolidation_function_id>
				<cdef_id>0</cdef_id>
				<value></value>
				<gprint_id>hash_060018e9c43831e54eca8069317a2ce8c6f751</gprint_id>
				<text_format>blockCacheCount</text_format>
				<hard_return></hard_return>
				<sequence>1</sequence>
			</hash_1000184f19880945b8a1847f225c00603e9f5f>
			<hash_100018c567d1fa25ab5578aa97f2c222be9db3>
				<task_item_id>hash_08001880aa850a079f23bd51d483bf5af8d670</task_item_id>
				<color_id>0</color_id>
				<alpha>FF</alpha>
				<graph_type_id>9</graph_type_id>
				<consolidation_function_id>4</consolidation_function_id>
				<cdef_id>0</cdef_id>
				<value></value>
				<gprint_id>hash_060018e9c43831e54eca8069317a2ce8c6f751</gprint_id>
				<text_format>Current:</text_format>
				<hard_return></hard_return>
				<sequence>2</sequence>
			</hash_100018c567d1fa25ab5578aa97f2c222be9db3>
			<hash_100018bd9b8785e1f4153e2b5289d3e9289015>
				<task_item_id>hash_08001880aa850a079f23bd51d483bf5af8d670</task_item_id>
				<color_id>0</color_id>
				<alpha>FF</alpha>
				<graph_type_id>9</graph_type_id>
				<consolidation_function_id>1</consolidation_function_id>
				<cdef_id>0</cdef_id>
				<value></value>
				<gprint_id>hash_060018e9c43831e54eca8069317a2ce8c6f751</gprint_id>
				<text_format>Average:</text_format>
				<hard_return></hard_return>
				<sequence>3</sequence>
			</hash_100018bd9b8785e1f4153e2b5289d3e9289015>
			<hash_1000187bb45c0ef4069b9deb2d679ea359cd00>
				<task_item_id>hash_08001880aa850a079f23bd51d483bf5af8d670</task_item_id>
				<color_id>0</color_id>
				<alpha>FF</alpha>
				<graph_type_id>9</graph_type_id>
				<consolidation_function_id>3</consolidation_function_id>
				<cdef_id>0</cdef_id>
				<value></value>
				<gprint_id>hash_060018e9c43831e54eca8069317a2ce8c6f751</gprint_id>
				<text_format>Maximum:</text_format>
				<hard_return>on</hard_return>
				<sequence>4</sequence>
			</hash_1000187bb45c0ef4069b9deb2d679ea359cd00>
		</items>
		<inputs>
			<hash_090018e33f1607cfd1689c94614d03d582a3a9>
				<name>Data Source [blockCacheCount]</name>
				<description></description>
				<column_name>task_item_id</column_name>
				<items>hash_0000184f19880945b8a1847f225c00603e9f5f|hash_000018c567d1fa25ab5578aa97f2c222be9db3|hash_000018bd9b8785e1f4153e2b5289d3e9289015|hash_0000187bb45c0ef4069b9deb2d679ea359cd00</items>
			</hash_090018e33f1607cfd1689c94614d03d582a3a9>
		</inputs>
	</hash_000018080f8e5b8333256f54d6f9754d8a7533>
	<hash_000018023b11dee7ac9ce024b2b51862d41616>
		<name>HBase 20.2 - RegionServer - Storefile Index Size</name>
		<graph>
			<t_title></t_title>
			<title>|host_description| HBase 20.2 - RegionServer - Storefile Index Size</title>
			<t_image_format_id></t_image_format_id>
			<image_format_id>1</image_format_id>
			<t_height></t_height>
			<height>120</height>
			<t_width></t_width>
			<width>500</width>
			<t_slope_mode></t_slope_mode>
			<slope_mode>on</slope_mode>
			<t_auto_scale></t_auto_scale>
			<auto_scale>on</auto_scale>
			<t_auto_scale_opts></t_auto_scale_opts>
			<auto_scale_opts>2</auto_scale_opts>
			<t_auto_scale_log></t_auto_scale_log>
			<auto_scale_log></auto_scale_log>
			<t_scale_log_units></t_scale_log_units>
			<scale_log_units></scale_log_units>
			<t_auto_scale_rigid></t_auto_scale_rigid>
			<auto_scale_rigid></auto_scale_rigid>
			<t_auto_padding></t_auto_padding>
			<auto_padding>on</auto_padding>
			<t_export></t_export>
			<export>on</export>
			<t_upper_limit></t_upper_limit>
			<upper_limit>100</upper_limit>
			<t_lower_limit></t_lower_limit>
			<lower_limit>0</lower_limit>
			<t_base_value></t_base_value>
			<base_value>1000</base_value>
			<t_unit_value></t_unit_value>
			<unit_value></unit_value>
			<t_unit_exponent_value></t_unit_exponent_value>
			<unit_exponent_value></unit_exponent_value>
			<t_vertical_label></t_vertical_label>
			<vertical_label></vertical_label>
		</graph>
		<items>
			<hash_100018bb665c1324d80b98a61206077dd2bb71>
				<task_item_id>hash_080018157c22684c830ff42323569597e77e01</task_item_id>
				<color_id>4444FF</color_id>
				<alpha>FF</alpha>
				<graph_type_id>7</graph_type_id>
				<consolidation_function_id>1</consolidation_function_id>
				<cdef_id>0</cdef_id>
				<value></value>
				<gprint_id>hash_060018e9c43831e54eca8069317a2ce8c6f751</gprint_id>
				<text_format>Store File Index Size MB</text_format>
				<hard_return></hard_return>
				<sequence>1</sequence>
			</hash_100018bb665c1324d80b98a61206077dd2bb71>
			<hash_1000186a3ee1f975bd4971619b7a14a5a15010>
				<task_item_id>hash_080018157c22684c830ff42323569597e77e01</task_item_id>
				<color_id>0</color_id>
				<alpha>FF</alpha>
				<graph_type_id>9</graph_type_id>
				<consolidation_function_id>4</consolidation_function_id>
				<cdef_id>0</cdef_id>
				<value></value>
				<gprint_id>hash_060018e9c43831e54eca8069317a2ce8c6f751</gprint_id>
				<text_format>Current:</text_format>
				<hard_return></hard_return>
				<sequence>2</sequence>
			</hash_1000186a3ee1f975bd4971619b7a14a5a15010>
			<hash_1000181839234a0b5a19d74a87a9ec02f88031>
				<task_item_id>hash_080018157c22684c830ff42323569597e77e01</task_item_id>
				<color_id>0</color_id>
				<alpha>FF</alpha>
				<graph_type_id>9</graph_type_id>
				<consolidation_function_id>1</consolidation_function_id>
				<cdef_id>0</cdef_id>
				<value></value>
				<gprint_id>hash_060018e9c43831e54eca8069317a2ce8c6f751</gprint_id>
				<text_format>Average:</text_format>
				<hard_return></hard_return>
				<sequence>3</sequence>
			</hash_1000181839234a0b5a19d74a87a9ec02f88031>
			<hash_1000180c9f2578ff662f0af0967a28aed1a97a>
				<task_item_id>hash_080018157c22684c830ff42323569597e77e01</task_item_id>
				<color_id>0</color_id>
				<alpha>FF</alpha>
				<graph_type_id>9</graph_type_id>
				<consolidation_function_id>3</consolidation_function_id>
				<cdef_id>0</cdef_id>
				<value></value>
				<gprint_id>hash_060018e9c43831e54eca8069317a2ce8c6f751</gprint_id>
				<text_format>Maximum:</text_format>
				<hard_return>on</hard_return>
				<sequence>4</sequence>
			</hash_1000180c9f2578ff662f0af0967a28aed1a97a>
		</items>
		<inputs>
			<hash_090018f84ef8d98f1b7ef99221798232f6d3b7>
				<name>Data Source [storefileIndexSizeM]</name>
				<description></description>
				<column_name>task_item_id</column_name>
				<items>hash_000018bb665c1324d80b98a61206077dd2bb71|hash_0000186a3ee1f975bd4971619b7a14a5a15010|hash_0000181839234a0b5a19d74a87a9ec02f88031|hash_0000180c9f2578ff662f0af0967a28aed1a97a</items>
			</hash_090018f84ef8d98f1b7ef99221798232f6d3b7>
		</inputs>
	</hash_000018023b11dee7ac9ce024b2b51862d41616>
	<hash_000018615daa4d4206777b88a13e4768149965>
		<name>HBase 20.2 - RegionServer - Memstore Size</name>
		<graph>
			<t_title></t_title>
			<title>|host_description| HBase 20.2 - RegionServer -  Memstore Size</title>
			<t_image_format_id></t_image_format_id>
			<image_format_id>1</image_format_id>
			<t_height></t_height>
			<height>120</height>
			<t_width></t_width>
			<width>500</width>
			<t_slope_mode></t_slope_mode>
			<slope_mode>on</slope_mode>
			<t_auto_scale></t_auto_scale>
			<auto_scale>on</auto_scale>
			<t_auto_scale_opts></t_auto_scale_opts>
			<auto_scale_opts>2</auto_scale_opts>
			<t_auto_scale_log></t_auto_scale_log>
			<auto_scale_log></auto_scale_log>
			<t_scale_log_units></t_scale_log_units>
			<scale_log_units></scale_log_units>
			<t_auto_scale_rigid></t_auto_scale_rigid>
			<auto_scale_rigid></auto_scale_rigid>
			<t_auto_padding></t_auto_padding>
			<auto_padding>on</auto_padding>
			<t_export></t_export>
			<export>on</export>
			<t_upper_limit></t_upper_limit>
			<upper_limit>100</upper_limit>
			<t_lower_limit></t_lower_limit>
			<lower_limit>0</lower_limit>
			<t_base_value></t_base_value>
			<base_value>1000</base_value>
			<t_unit_value></t_unit_value>
			<unit_value></unit_value>
			<t_unit_exponent_value></t_unit_exponent_value>
			<unit_exponent_value></unit_exponent_value>
			<t_vertical_label></t_vertical_label>
			<vertical_label></vertical_label>
		</graph>
		<items>
			<hash_100018a90cdc76bb456fe93c25dff2b978c5d2>
				<task_item_id>hash_080018ea154ffb6e47da15a87158d1899b5738</task_item_id>
				<color_id>4444FF</color_id>
				<alpha>FF</alpha>
				<graph_type_id>7</graph_type_id>
				<consolidation_function_id>1</consolidation_function_id>
				<cdef_id>0</cdef_id>
				<value></value>
				<gprint_id>hash_060018e9c43831e54eca8069317a2ce8c6f751</gprint_id>
				<text_format>Memstore Size MB</text_format>
				<hard_return></hard_return>
				<sequence>1</sequence>
			</hash_100018a90cdc76bb456fe93c25dff2b978c5d2>
			<hash_1000187ecba382eece7d4f2f5566c07f57f3e7>
				<task_item_id>hash_080018ea154ffb6e47da15a87158d1899b5738</task_item_id>
				<color_id>0</color_id>
				<alpha>FF</alpha>
				<graph_type_id>9</graph_type_id>
				<consolidation_function_id>4</consolidation_function_id>
				<cdef_id>0</cdef_id>
				<value></value>
				<gprint_id>hash_060018e9c43831e54eca8069317a2ce8c6f751</gprint_id>
				<text_format>Current:</text_format>
				<hard_return></hard_return>
				<sequence>2</sequence>
			</hash_1000187ecba382eece7d4f2f5566c07f57f3e7>
			<hash_1000189f8215db668551741837974121994236>
				<task_item_id>hash_080018ea154ffb6e47da15a87158d1899b5738</task_item_id>
				<color_id>0</color_id>
				<alpha>FF</alpha>
				<graph_type_id>9</graph_type_id>
				<consolidation_function_id>1</consolidation_function_id>
				<cdef_id>0</cdef_id>
				<value></value>
				<gprint_id>hash_060018e9c43831e54eca8069317a2ce8c6f751</gprint_id>
				<text_format>Average:</text_format>
				<hard_return></hard_return>
				<sequence>3</sequence>
			</hash_1000189f8215db668551741837974121994236>
			<hash_100018437cc323161fcf1a1ad12600db6858a8>
				<task_item_id>hash_080018ea154ffb6e47da15a87158d1899b5738</task_item_id>
				<color_id>0</color_id>
				<alpha>FF</alpha>
				<graph_type_id>9</graph_type_id>
				<consolidation_function_id>3</consolidation_function_id>
				<cdef_id>0</cdef_id>
				<value></value>
				<gprint_id>hash_060018e9c43831e54eca8069317a2ce8c6f751</gprint_id>
				<text_format>Maximum:</text_format>
				<hard_return>on</hard_return>
				<sequence>4</sequence>
			</hash_100018437cc323161fcf1a1ad12600db6858a8>
		</items>
		<inputs>
			<hash_09001834c333bd8d7a7a86f55b4103486ff38e>
				<name>Data Source [memstoreSizeMB]</name>
				<description></description>
				<column_name>task_item_id</column_name>
				<items>hash_000018a90cdc76bb456fe93c25dff2b978c5d2|hash_0000187ecba382eece7d4f2f5566c07f57f3e7|hash_0000189f8215db668551741837974121994236|hash_000018437cc323161fcf1a1ad12600db6858a8</items>
			</hash_09001834c333bd8d7a7a86f55b4103486ff38e>
		</inputs>
	</hash_000018615daa4d4206777b88a13e4768149965>
	<hash_000018feb34a939aebdce29b2769157f178995>
		<name>HBase 20.2 - RegionServer - Atomic Incr</name>
		<graph>
			<t_title></t_title>
			<title>|host_description| HBase 20.2 - RegionServer - Atomic Incr</title>
			<t_image_format_id></t_image_format_id>
			<image_format_id>1</image_format_id>
			<t_height></t_height>
			<height>120</height>
			<t_width></t_width>
			<width>500</width>
			<t_slope_mode></t_slope_mode>
			<slope_mode>on</slope_mode>
			<t_auto_scale></t_auto_scale>
			<auto_scale>on</auto_scale>
			<t_auto_scale_opts></t_auto_scale_opts>
			<auto_scale_opts>2</auto_scale_opts>
			<t_auto_scale_log></t_auto_scale_log>
			<auto_scale_log></auto_scale_log>
			<t_scale_log_units></t_scale_log_units>
			<scale_log_units></scale_log_units>
			<t_auto_scale_rigid></t_auto_scale_rigid>
			<auto_scale_rigid></auto_scale_rigid>
			<t_auto_padding></t_auto_padding>
			<auto_padding>on</auto_padding>
			<t_export></t_export>
			<export>on</export>
			<t_upper_limit></t_upper_limit>
			<upper_limit>100</upper_limit>
			<t_lower_limit></t_lower_limit>
			<lower_limit>0</lower_limit>
			<t_base_value></t_base_value>
			<base_value>1000</base_value>
			<t_unit_value></t_unit_value>
			<unit_value></unit_value>
			<t_unit_exponent_value></t_unit_exponent_value>
			<unit_exponent_value></unit_exponent_value>
			<t_vertical_label></t_vertical_label>
			<vertical_label></vertical_label>
		</graph>
		<items>
			<hash_100018cc815c03ac434d81c5bc4720130548d6>
				<task_item_id>hash_080018bbd4e2b198c34b946dd8485b9da1d6a5</task_item_id>
				<color_id>4444FF</color_id>
				<alpha>FF</alpha>
				<graph_type_id>5</graph_type_id>
				<consolidation_function_id>1</consolidation_function_id>
				<cdef_id>0</cdef_id>
				<value></value>
				<gprint_id>hash_060018e9c43831e54eca8069317a2ce8c6f751</gprint_id>
				<text_format>avg</text_format>
				<hard_return></hard_return>
				<sequence>1</sequence>
			</hash_100018cc815c03ac434d81c5bc4720130548d6>
			<hash_100018fe7b68c7f6c70b0c247af5bd7ca24c27>
				<task_item_id>hash_080018bbd4e2b198c34b946dd8485b9da1d6a5</task_item_id>
				<color_id>0</color_id>
				<alpha>FF</alpha>
				<graph_type_id>9</graph_type_id>
				<consolidation_function_id>4</consolidation_function_id>
				<cdef_id>0</cdef_id>
				<value></value>
				<gprint_id>hash_060018e9c43831e54eca8069317a2ce8c6f751</gprint_id>
				<text_format>Current:</text_format>
				<hard_return></hard_return>
				<sequence>2</sequence>
			</hash_100018fe7b68c7f6c70b0c247af5bd7ca24c27>
			<hash_1000185c689fcaf56748bdb5b1ac98a68a68ee>
				<task_item_id>hash_080018bbd4e2b198c34b946dd8485b9da1d6a5</task_item_id>
				<color_id>0</color_id>
				<alpha>FF</alpha>
				<graph_type_id>9</graph_type_id>
				<consolidation_function_id>1</consolidation_function_id>
				<cdef_id>0</cdef_id>
				<value></value>
				<gprint_id>hash_060018e9c43831e54eca8069317a2ce8c6f751</gprint_id>
				<text_format>Average:</text_format>
				<hard_return></hard_return>
				<sequence>3</sequence>
			</hash_1000185c689fcaf56748bdb5b1ac98a68a68ee>
			<hash_1000186210a344c3c5706a4529c534663ff3a5>
				<task_item_id>hash_080018bbd4e2b198c34b946dd8485b9da1d6a5</task_item_id>
				<color_id>0</color_id>
				<alpha>FF</alpha>
				<graph_type_id>9</graph_type_id>
				<consolidation_function_id>3</consolidation_function_id>
				<cdef_id>0</cdef_id>
				<value></value>
				<gprint_id>hash_060018e9c43831e54eca8069317a2ce8c6f751</gprint_id>
				<text_format>Maximum:</text_format>
				<hard_return>on</hard_return>
				<sequence>4</sequence>
			</hash_1000186210a344c3c5706a4529c534663ff3a5>
			<hash_1000183da716e26e61d9760c21587440c1e220>
				<task_item_id>hash_080018dcb1c106027b9100fd49fdbb37d5f4a6</task_item_id>
				<color_id>FF0000</color_id>
				<alpha>FF</alpha>
				<graph_type_id>5</graph_type_id>
				<consolidation_function_id>1</consolidation_function_id>
				<cdef_id>0</cdef_id>
				<value></value>
				<gprint_id>hash_060018e9c43831e54eca8069317a2ce8c6f751</gprint_id>
				<text_format>max</text_format>
				<hard_return></hard_return>
				<sequence>5</sequence>
			</hash_1000183da716e26e61d9760c21587440c1e220>
			<hash_10001818e509add877564a1736b3fa016900e8>
				<task_item_id>hash_080018dcb1c106027b9100fd49fdbb37d5f4a6</task_item_id>
				<color_id>0</color_id>
				<alpha>FF</alpha>
				<graph_type_id>9</graph_type_id>
				<consolidation_function_id>4</consolidation_function_id>
				<cdef_id>0</cdef_id>
				<value></value>
				<gprint_id>hash_060018e9c43831e54eca8069317a2ce8c6f751</gprint_id>
				<text_format>Current:</text_format>
				<hard_return></hard_return>
				<sequence>6</sequence>
			</hash_10001818e509add877564a1736b3fa016900e8>
			<hash_100018a184c95b1b3695781491cf4d00ef9a12>
				<task_item_id>hash_080018dcb1c106027b9100fd49fdbb37d5f4a6</task_item_id>
				<color_id>0</color_id>
				<alpha>FF</alpha>
				<graph_type_id>9</graph_type_id>
				<consolidation_function_id>1</consolidation_function_id>
				<cdef_id>0</cdef_id>
				<value></value>
				<gprint_id>hash_060018e9c43831e54eca8069317a2ce8c6f751</gprint_id>
				<text_format>Average:</text_format>
				<hard_return></hard_return>
				<sequence>7</sequence>
			</hash_100018a184c95b1b3695781491cf4d00ef9a12>
			<hash_100018b07db57ffc390eec69c2f7e39b97d112>
				<task_item_id>hash_080018dcb1c106027b9100fd49fdbb37d5f4a6</task_item_id>
				<color_id>0</color_id>
				<alpha>FF</alpha>
				<graph_type_id>9</graph_type_id>
				<consolidation_function_id>3</consolidation_function_id>
				<cdef_id>0</cdef_id>
				<value></value>
				<gprint_id>hash_060018e9c43831e54eca8069317a2ce8c6f751</gprint_id>
				<text_format>Maximum:</text_format>
				<hard_return>on</hard_return>
				<sequence>8</sequence>
			</hash_100018b07db57ffc390eec69c2f7e39b97d112>
			<hash_1000185045d2cbd75476b2bec742c95766f449>
				<task_item_id>hash_0800180c5a36d27b37ec616db09745d28d18ee</task_item_id>
				<color_id>00FF00</color_id>
				<alpha>FF</alpha>
				<graph_type_id>5</graph_type_id>
				<consolidation_function_id>1</consolidation_function_id>
				<cdef_id>0</cdef_id>
				<value></value>
				<gprint_id>hash_060018e9c43831e54eca8069317a2ce8c6f751</gprint_id>
				<text_format>min</text_format>
				<hard_return></hard_return>
				<sequence>9</sequence>
			</hash_1000185045d2cbd75476b2bec742c95766f449>
			<hash_100018125cb5c9f6e415f19c8b984bd8b33d7c>
				<task_item_id>hash_0800180c5a36d27b37ec616db09745d28d18ee</task_item_id>
				<color_id>0</color_id>
				<alpha>FF</alpha>
				<graph_type_id>9</graph_type_id>
				<consolidation_function_id>4</consolidation_function_id>
				<cdef_id>0</cdef_id>
				<value></value>
				<gprint_id>hash_060018e9c43831e54eca8069317a2ce8c6f751</gprint_id>
				<text_format>Current:</text_format>
				<hard_return></hard_return>
				<sequence>10</sequence>
			</hash_100018125cb5c9f6e415f19c8b984bd8b33d7c>
			<hash_100018ca0e97ed515c9408282a1806ab2e483d>
				<task_item_id>hash_0800180c5a36d27b37ec616db09745d28d18ee</task_item_id>
				<color_id>0</color_id>
				<alpha>FF</alpha>
				<graph_type_id>9</graph_type_id>
				<consolidation_function_id>1</consolidation_function_id>
				<cdef_id>0</cdef_id>
				<value></value>
				<gprint_id>hash_060018e9c43831e54eca8069317a2ce8c6f751</gprint_id>
				<text_format>Average:</text_format>
				<hard_return></hard_return>
				<sequence>11</sequence>
			</hash_100018ca0e97ed515c9408282a1806ab2e483d>
			<hash_100018eba007f3a23b37aabd0f5a9abf65df70>
				<task_item_id>hash_0800180c5a36d27b37ec616db09745d28d18ee</task_item_id>
				<color_id>0</color_id>
				<alpha>FF</alpha>
				<graph_type_id>9</graph_type_id>
				<consolidation_function_id>3</consolidation_function_id>
				<cdef_id>0</cdef_id>
				<value></value>
				<gprint_id>hash_060018e9c43831e54eca8069317a2ce8c6f751</gprint_id>
				<text_format>Maximum:</text_format>
				<hard_return>on</hard_return>
				<sequence>12</sequence>
			</hash_100018eba007f3a23b37aabd0f5a9abf65df70>
			<hash_100018a8f0679c4fc797107ccd3ad7347c563c>
				<task_item_id>hash_0800180f4a05a56203d40bae4a7feee1615919</task_item_id>
				<color_id>000000</color_id>
				<alpha>FF</alpha>
				<graph_type_id>5</graph_type_id>
				<consolidation_function_id>1</consolidation_function_id>
				<cdef_id>0</cdef_id>
				<value></value>
				<gprint_id>hash_060018e9c43831e54eca8069317a2ce8c6f751</gprint_id>
				<text_format>NumOps</text_format>
				<hard_return></hard_return>
				<sequence>13</sequence>
			</hash_100018a8f0679c4fc797107ccd3ad7347c563c>
			<hash_1000186e5bde1dd3713f52e9883e9bed1998f9>
				<task_item_id>hash_0800180f4a05a56203d40bae4a7feee1615919</task_item_id>
				<color_id>0</color_id>
				<alpha>FF</alpha>
				<graph_type_id>9</graph_type_id>
				<consolidation_function_id>4</consolidation_function_id>
				<cdef_id>0</cdef_id>
				<value></value>
				<gprint_id>hash_060018e9c43831e54eca8069317a2ce8c6f751</gprint_id>
				<text_format>Current:</text_format>
				<hard_return></hard_return>
				<sequence>14</sequence>
			</hash_1000186e5bde1dd3713f52e9883e9bed1998f9>
			<hash_100018d5ea64ae126093236c9dbe4cc120b7fb>
				<task_item_id>hash_0800180f4a05a56203d40bae4a7feee1615919</task_item_id>
				<color_id>0</color_id>
				<alpha>FF</alpha>
				<graph_type_id>9</graph_type_id>
				<consolidation_function_id>1</consolidation_function_id>
				<cdef_id>0</cdef_id>
				<value></value>
				<gprint_id>hash_060018e9c43831e54eca8069317a2ce8c6f751</gprint_id>
				<text_format>Average:</text_format>
				<hard_return></hard_return>
				<sequence>15</sequence>
			</hash_100018d5ea64ae126093236c9dbe4cc120b7fb>
			<hash_100018b5029be840465f09fea8fe74f342ceb6>
				<task_item_id>hash_0800180f4a05a56203d40bae4a7feee1615919</task_item_id>
				<color_id>0</color_id>
				<alpha>FF</alpha>
				<graph_type_id>9</graph_type_id>
				<consolidation_function_id>3</consolidation_function_id>
				<cdef_id>0</cdef_id>
				<value></value>
				<gprint_id>hash_060018e9c43831e54eca8069317a2ce8c6f751</gprint_id>
				<text_format>Maximum:</text_format>
				<hard_return>on</hard_return>
				<sequence>16</sequence>
			</hash_100018b5029be840465f09fea8fe74f342ceb6>
		</items>
		<inputs>
			<hash_09001855972cbd363a67932aeac9f187a69c77>
				<name>Data Source [atomicIncrementAvg]</name>
				<description></description>
				<column_name>task_item_id</column_name>
				<items>hash_000018cc815c03ac434d81c5bc4720130548d6|hash_000018fe7b68c7f6c70b0c247af5bd7ca24c27|hash_0000185c689fcaf56748bdb5b1ac98a68a68ee|hash_0000186210a344c3c5706a4529c534663ff3a5</items>
			</hash_09001855972cbd363a67932aeac9f187a69c77>
			<hash_090018a45fcc059574cfdee54c1686d3a90fe5>
				<name>Data Source [atomicIncrementMax]</name>
				<description></description>
				<column_name>task_item_id</column_name>
				<items>hash_0000183da716e26e61d9760c21587440c1e220|hash_00001818e509add877564a1736b3fa016900e8|hash_000018a184c95b1b3695781491cf4d00ef9a12|hash_000018b07db57ffc390eec69c2f7e39b97d112</items>
			</hash_090018a45fcc059574cfdee54c1686d3a90fe5>
			<hash_09001866946fe97307cff3988ea4ed565ef794>
				<name>Data Source [atomicIncrementMin]</name>
				<description></description>
				<column_name>task_item_id</column_name>
				<items>hash_0000185045d2cbd75476b2bec742c95766f449|hash_000018125cb5c9f6e415f19c8b984bd8b33d7c|hash_000018ca0e97ed515c9408282a1806ab2e483d|hash_000018eba007f3a23b37aabd0f5a9abf65df70</items>
			</hash_09001866946fe97307cff3988ea4ed565ef794>
			<hash_090018b842cbd55335643aa64ecb62f5676c2d>
				<name>Data Source [atomicIncrementNumO]</name>
				<description></description>
				<column_name>task_item_id</column_name>
				<items>hash_000018a8f0679c4fc797107ccd3ad7347c563c|hash_0000186e5bde1dd3713f52e9883e9bed1998f9|hash_000018d5ea64ae126093236c9dbe4cc120b7fb|hash_000018b5029be840465f09fea8fe74f342ceb6</items>
			</hash_090018b842cbd55335643aa64ecb62f5676c2d>
		</inputs>
	</hash_000018feb34a939aebdce29b2769157f178995>
	<hash_010018a82de624f8645dc034167a26c383a230>
		<name>HBase 20.2- RegionServer - RegionServerStatistics</name>
		<ds>
			<t_name></t_name>
			<name>|host_description| HBase 20.2- RegionServer - RegionServerStatistics</name>
			<data_input_id>hash_030018b6c3fc6020cada88de08ebae65b1efe9</data_input_id>
			<t_rra_id></t_rra_id>
			<t_rrd_step></t_rrd_step>
			<rrd_step>300</rrd_step>
			<t_active></t_active>
			<active>on</active>
			<rra_items>hash_150018c21df5178e5c955013591239eb0afd46|hash_1500180d9c0af8b8acdc7807943937b3208e29|hash_1500186fc2d038fb42950138b0ce3e9874cc60|hash_150018e36f3adb9f152adfa5dc50fd2b23337e</rra_items>
		</ds>
		<items>
			<hash_0800180ffd839156564e6446f6d802d1894a4c>
				<t_data_source_name></t_data_source_name>
				<data_source_name>storefiles</data_source_name>
				<t_rrd_minimum></t_rrd_minimum>
				<rrd_minimum>0</rrd_minimum>
				<t_rrd_maximum></t_rrd_maximum>
				<rrd_maximum>0</rrd_maximum>
				<t_data_source_type_id></t_data_source_type_id>
				<data_source_type_id>1</data_source_type_id>
				<t_rrd_heartbeat></t_rrd_heartbeat>
				<rrd_heartbeat>600</rrd_heartbeat>
				<t_data_input_field_id></t_data_input_field_id>
				<data_input_field_id>hash_070018c5394a4baece7df6e80da807f4a03fc6</data_input_field_id>
			</hash_0800180ffd839156564e6446f6d802d1894a4c>
			<hash_0800185ac598247dca64fdc2b09b75b7aee189>
				<t_data_source_name></t_data_source_name>
				<data_source_name>blockCacheFree</data_source_name>
				<t_rrd_minimum></t_rrd_minimum>
				<rrd_minimum>0</rrd_minimum>
				<t_rrd_maximum></t_rrd_maximum>
				<rrd_maximum>0</rrd_maximum>
				<t_data_source_type_id></t_data_source_type_id>
				<data_source_type_id>1</data_source_type_id>
				<t_rrd_heartbeat></t_rrd_heartbeat>
				<rrd_heartbeat>600</rrd_heartbeat>
				<t_data_input_field_id></t_data_input_field_id>
				<data_input_field_id>hash_070018ec524232cfeb7f309d62291974712c94</data_input_field_id>
			</hash_0800185ac598247dca64fdc2b09b75b7aee189>
			<hash_080018157c22684c830ff42323569597e77e01>
				<t_data_source_name></t_data_source_name>
				<data_source_name>storefileIndexSizeM</data_source_name>
				<t_rrd_minimum></t_rrd_minimum>
				<rrd_minimum>0</rrd_minimum>
				<t_rrd_maximum></t_rrd_maximum>
				<rrd_maximum>0</rrd_maximum>
				<t_data_source_type_id></t_data_source_type_id>
				<data_source_type_id>1</data_source_type_id>
				<t_rrd_heartbeat></t_rrd_heartbeat>
				<rrd_heartbeat>600</rrd_heartbeat>
				<t_data_input_field_id></t_data_input_field_id>
				<data_input_field_id>hash_0700187b9dc2baea29d0cfc75ef3deb2270ce5</data_input_field_id>
			</hash_080018157c22684c830ff42323569597e77e01>
			<hash_080018ea154ffb6e47da15a87158d1899b5738>
				<t_data_source_name></t_data_source_name>
				<data_source_name>memstoreSizeMB</data_source_name>
				<t_rrd_minimum></t_rrd_minimum>
				<rrd_minimum>0</rrd_minimum>
				<t_rrd_maximum></t_rrd_maximum>
				<rrd_maximum>100</rrd_maximum>
				<t_data_source_type_id></t_data_source_type_id>
				<data_source_type_id>1</data_source_type_id>
				<t_rrd_heartbeat></t_rrd_heartbeat>
				<rrd_heartbeat>600</rrd_heartbeat>
				<t_data_input_field_id></t_data_input_field_id>
				<data_input_field_id>hash_070018d7cb89191a7e171ba5194bc053d64d59</data_input_field_id>
			</hash_080018ea154ffb6e47da15a87158d1899b5738>
			<hash_080018886eefbd178be1cc17b3ee37d906bb08>
				<t_data_source_name></t_data_source_name>
				<data_source_name>stores</data_source_name>
				<t_rrd_minimum></t_rrd_minimum>
				<rrd_minimum>0</rrd_minimum>
				<t_rrd_maximum></t_rrd_maximum>
				<rrd_maximum>0</rrd_maximum>
				<t_data_source_type_id></t_data_source_type_id>
				<data_source_type_id>1</data_source_type_id>
				<t_rrd_heartbeat></t_rrd_heartbeat>
				<rrd_heartbeat>600</rrd_heartbeat>
				<t_data_input_field_id></t_data_input_field_id>
				<data_input_field_id>hash_070018bb8e6f1dbca52def572a925c007cec2a</data_input_field_id>
			</hash_080018886eefbd178be1cc17b3ee37d906bb08>
			<hash_08001880aa850a079f23bd51d483bf5af8d670>
				<t_data_source_name></t_data_source_name>
				<data_source_name>blockCacheCount</data_source_name>
				<t_rrd_minimum></t_rrd_minimum>
				<rrd_minimum>0</rrd_minimum>
				<t_rrd_maximum></t_rrd_maximum>
				<rrd_maximum>0</rrd_maximum>
				<t_data_source_type_id></t_data_source_type_id>
				<data_source_type_id>1</data_source_type_id>
				<t_rrd_heartbeat></t_rrd_heartbeat>
				<rrd_heartbeat>600</rrd_heartbeat>
				<t_data_input_field_id></t_data_input_field_id>
				<data_input_field_id>hash_070018e91efdab7042e8de45fe539cb494849c</data_input_field_id>
			</hash_08001880aa850a079f23bd51d483bf5af8d670>
			<hash_080018dc0313937a701c83b6986ac43dfbb30f>
				<t_data_source_name></t_data_source_name>
				<data_source_name>regions</data_source_name>
				<t_rrd_minimum></t_rrd_minimum>
				<rrd_minimum>0</rrd_minimum>
				<t_rrd_maximum></t_rrd_maximum>
				<rrd_maximum>0</rrd_maximum>
				<t_data_source_type_id></t_data_source_type_id>
				<data_source_type_id>1</data_source_type_id>
				<t_rrd_heartbeat></t_rrd_heartbeat>
				<rrd_heartbeat>600</rrd_heartbeat>
				<t_data_input_field_id></t_data_input_field_id>
				<data_input_field_id>hash_070018869356c7944caad81f1ec9e304353a49</data_input_field_id>
			</hash_080018dc0313937a701c83b6986ac43dfbb30f>
			<hash_080018eb14139528c7814c4a9a55fd5727bf62>
				<t_data_source_name></t_data_source_name>
				<data_source_name>blockCacheSize</data_source_name>
				<t_rrd_minimum></t_rrd_minimum>
				<rrd_minimum>0</rrd_minimum>
				<t_rrd_maximum></t_rrd_maximum>
				<rrd_maximum>0</rrd_maximum>
				<t_data_source_type_id></t_data_source_type_id>
				<data_source_type_id>1</data_source_type_id>
				<t_rrd_heartbeat></t_rrd_heartbeat>
				<rrd_heartbeat>600</rrd_heartbeat>
				<t_data_input_field_id></t_data_input_field_id>
				<data_input_field_id>hash_07001858c3ef39e1dcb4bdedbfd025146bd579</data_input_field_id>
			</hash_080018eb14139528c7814c4a9a55fd5727bf62>
			<hash_0800180f4a05a56203d40bae4a7feee1615919>
				<t_data_source_name></t_data_source_name>
				<data_source_name>atomicIncrementNumO</data_source_name>
				<t_rrd_minimum></t_rrd_minimum>
				<rrd_minimum>0</rrd_minimum>
				<t_rrd_maximum></t_rrd_maximum>
				<rrd_maximum>0</rrd_maximum>
				<t_data_source_type_id></t_data_source_type_id>
				<data_source_type_id>1</data_source_type_id>
				<t_rrd_heartbeat></t_rrd_heartbeat>
				<rrd_heartbeat>600</rrd_heartbeat>
				<t_data_input_field_id></t_data_input_field_id>
				<data_input_field_id>hash_070018649a28926034d8b67867fd064bf31584</data_input_field_id>
			</hash_0800180f4a05a56203d40bae4a7feee1615919>
			<hash_0800180c5a36d27b37ec616db09745d28d18ee>
				<t_data_source_name></t_data_source_name>
				<data_source_name>atomicIncrementMin</data_source_name>
				<t_rrd_minimum></t_rrd_minimum>
				<rrd_minimum>0</rrd_minimum>
				<t_rrd_maximum></t_rrd_maximum>
				<rrd_maximum>100</rrd_maximum>
				<t_data_source_type_id></t_data_source_type_id>
				<data_source_type_id>1</data_source_type_id>
				<t_rrd_heartbeat></t_rrd_heartbeat>
				<rrd_heartbeat>600</rrd_heartbeat>
				<t_data_input_field_id></t_data_input_field_id>
				<data_input_field_id>hash_0700184f99a5285f93c7df9558cba82f3671a8</data_input_field_id>
			</hash_0800180c5a36d27b37ec616db09745d28d18ee>
			<hash_080018605955075e17f25b7a4a601cc2cc5e5a>
				<t_data_source_name></t_data_source_name>
				<data_source_name>blockCacheHitRatio</data_source_name>
				<t_rrd_minimum></t_rrd_minimum>
				<rrd_minimum>0</rrd_minimum>
				<t_rrd_maximum></t_rrd_maximum>
				<rrd_maximum>0</rrd_maximum>
				<t_data_source_type_id></t_data_source_type_id>
				<data_source_type_id>1</data_source_type_id>
				<t_rrd_heartbeat></t_rrd_heartbeat>
				<rrd_heartbeat>600</rrd_heartbeat>
				<t_data_input_field_id></t_data_input_field_id>
				<data_input_field_id>hash_070018561cd3c8ae0ccdbab97d318fbf18a89c</data_input_field_id>
			</hash_080018605955075e17f25b7a4a601cc2cc5e5a>
			<hash_080018dcb1c106027b9100fd49fdbb37d5f4a6>
				<t_data_source_name></t_data_source_name>
				<data_source_name>atomicIncrementMax</data_source_name>
				<t_rrd_minimum></t_rrd_minimum>
				<rrd_minimum>0</rrd_minimum>
				<t_rrd_maximum></t_rrd_maximum>
				<rrd_maximum>0</rrd_maximum>
				<t_data_source_type_id></t_data_source_type_id>
				<data_source_type_id>1</data_source_type_id>
				<t_rrd_heartbeat></t_rrd_heartbeat>
				<rrd_heartbeat>600</rrd_heartbeat>
				<t_data_input_field_id></t_data_input_field_id>
				<data_input_field_id>hash_070018ad8edbaeea8ad6969d656b03db033155</data_input_field_id>
			</hash_080018dcb1c106027b9100fd49fdbb37d5f4a6>
			<hash_080018bbd4e2b198c34b946dd8485b9da1d6a5>
				<t_data_source_name></t_data_source_name>
				<data_source_name>atomicIncrementAvg</data_source_name>
				<t_rrd_minimum></t_rrd_minimum>
				<rrd_minimum>0</rrd_minimum>
				<t_rrd_maximum></t_rrd_maximum>
				<rrd_maximum>0</rrd_maximum>
				<t_data_source_type_id></t_data_source_type_id>
				<data_source_type_id>1</data_source_type_id>
				<t_rrd_heartbeat></t_rrd_heartbeat>
				<rrd_heartbeat>600</rrd_heartbeat>
				<t_data_input_field_id></t_data_input_field_id>
				<data_input_field_id>hash_070018902fe03a77f910a8eb358feffc6ee809</data_input_field_id>
			</hash_080018bbd4e2b198c34b946dd8485b9da1d6a5>
		</items>
		<data>
			<item_000>
				<data_input_field_id>hash_07001896e7a2f77fe59e4f25e1ac50fab2fe77</data_input_field_id>
				<t_value>on</t_value>
				<value>hadoop:name=RegionServerStatistics,service=RegionServer</value>
			</item_000>
			<item_001>
				<data_input_field_id>hash_070018020bc51d93c15506184bea904497f39a</data_input_field_id>
				<t_value>on</t_value>
				<value>password</value>
			</item_001>
			<item_002>
				<data_input_field_id>hash_070018e994773135c00063584f6291d477d04d</data_input_field_id>
				<t_value>on</t_value>
				<value>controlRole</value>
			</item_002>
			<item_003>
				<data_input_field_id>hash_070018906a11baf1cedd1dc7b7aaae36497e8f</data_input_field_id>
				<t_value>on</t_value>
				<value>service:jmx:rmi:///jndi/rmi://10.0.24.1:10102/jmxrmi</value>
			</item_003>
		</data>
	</hash_010018a82de624f8645dc034167a26c383a230>
	<hash_030018b6c3fc6020cada88de08ebae65b1efe9>
		<name>HBase 20.2- RegionServer - RegionServerStatistics</name>
		<type_id>1</type_id>
		<input_string>sh &lt;path_cacti&gt;/scripts/0_20/regionserver/RegionServerStatistics.sh &lt;jmx_url&gt; &lt;user&gt; &lt;pass&gt; &lt;object&gt;</input_string>
		<fields>
			<hash_070018906a11baf1cedd1dc7b7aaae36497e8f>
				<name>jmx_url</name>
				<update_rra></update_rra>
				<regexp_match></regexp_match>
				<allow_nulls></allow_nulls>
				<type_code></type_code>
				<input_output>in</input_output>
				<data_name>jmx_url</data_name>
			</hash_070018906a11baf1cedd1dc7b7aaae36497e8f>
			<hash_070018e994773135c00063584f6291d477d04d>
				<name>user</name>
				<update_rra></update_rra>
				<regexp_match></regexp_match>
				<allow_nulls></allow_nulls>
				<type_code></type_code>
				<input_output>in</input_output>
				<data_name>user</data_name>
			</hash_070018e994773135c00063584f6291d477d04d>
			<hash_070018020bc51d93c15506184bea904497f39a>
				<name>pass</name>
				<update_rra></update_rra>
				<regexp_match></regexp_match>
				<allow_nulls></allow_nulls>
				<type_code></type_code>
				<input_output>in</input_output>
				<data_name>pass</data_name>
			</hash_070018020bc51d93c15506184bea904497f39a>
			<hash_07001896e7a2f77fe59e4f25e1ac50fab2fe77>
				<name>object</name>
				<update_rra></update_rra>
				<regexp_match></regexp_match>
				<allow_nulls></allow_nulls>
				<type_code></type_code>
				<input_output>in</input_output>
				<data_name>object</data_name>
			</hash_07001896e7a2f77fe59e4f25e1ac50fab2fe77>
			<hash_070018c5394a4baece7df6e80da807f4a03fc6>
				<name>storefiles</name>
				<update_rra>on</update_rra>
				<regexp_match></regexp_match>
				<allow_nulls></allow_nulls>
				<type_code></type_code>
				<input_output>out</input_output>
				<data_name>storefiles</data_name>
			</hash_070018c5394a4baece7df6e80da807f4a03fc6>
			<hash_070018ec524232cfeb7f309d62291974712c94>
				<name>blockCacheFree</name>
				<update_rra>on</update_rra>
				<regexp_match></regexp_match>
				<allow_nulls></allow_nulls>
				<type_code></type_code>
				<input_output>out</input_output>
				<data_name>blockCacheFree</data_name>
			</hash_070018ec524232cfeb7f309d62291974712c94>
			<hash_0700187b9dc2baea29d0cfc75ef3deb2270ce5>
				<name>storefileIndexSizeMB</name>
				<update_rra>on</update_rra>
				<regexp_match></regexp_match>
				<allow_nulls></allow_nulls>
				<type_code></type_code>
				<input_output>out</input_output>
				<data_name>storefileIndexSizeMB</data_name>
			</hash_0700187b9dc2baea29d0cfc75ef3deb2270ce5>
			<hash_070018d7cb89191a7e171ba5194bc053d64d59>
				<name>memstoreSizeMB</name>
				<update_rra>on</update_rra>
				<regexp_match></regexp_match>
				<allow_nulls></allow_nulls>
				<type_code></type_code>
				<input_output>out</input_output>
				<data_name>memstoreSizeMB</data_name>
			</hash_070018d7cb89191a7e171ba5194bc053d64d59>
			<hash_070018bb8e6f1dbca52def572a925c007cec2a>
				<name>stores</name>
				<update_rra>on</update_rra>
				<regexp_match></regexp_match>
				<allow_nulls></allow_nulls>
				<type_code></type_code>
				<input_output>out</input_output>
				<data_name>stores</data_name>
			</hash_070018bb8e6f1dbca52def572a925c007cec2a>
			<hash_070018e91efdab7042e8de45fe539cb494849c>
				<name>blockCacheCount</name>
				<update_rra>on</update_rra>
				<regexp_match></regexp_match>
				<allow_nulls></allow_nulls>
				<type_code></type_code>
				<input_output>out</input_output>
				<data_name>blockCacheCount</data_name>
			</hash_070018e91efdab7042e8de45fe539cb494849c>
			<hash_070018869356c7944caad81f1ec9e304353a49>
				<name>regions</name>
				<update_rra>on</update_rra>
				<regexp_match></regexp_match>
				<allow_nulls></allow_nulls>
				<type_code></type_code>
				<input_output>out</input_output>
				<data_name>regions</data_name>
			</hash_070018869356c7944caad81f1ec9e304353a49>
			<hash_070018561cd3c8ae0ccdbab97d318fbf18a89c>
				<name>blockCacheHitRatio</name>
				<update_rra>on</update_rra>
				<regexp_match></regexp_match>
				<allow_nulls></allow_nulls>
				<type_code></type_code>
				<input_output>out</input_output>
				<data_name>blockCacheHitRatio</data_name>
			</hash_070018561cd3c8ae0ccdbab97d318fbf18a89c>
			<hash_07001858c3ef39e1dcb4bdedbfd025146bd579>
				<name>blockCacheSize</name>
				<update_rra>on</update_rra>
				<regexp_match></regexp_match>
				<allow_nulls></allow_nulls>
				<type_code></type_code>
				<input_output>out</input_output>
				<data_name>blockCacheSize</data_name>
			</hash_07001858c3ef39e1dcb4bdedbfd025146bd579>
			<hash_070018649a28926034d8b67867fd064bf31584>
				<name>atomicIncrementTimeNumOps</name>
				<update_rra>on</update_rra>
				<regexp_match></regexp_match>
				<allow_nulls></allow_nulls>
				<type_code></type_code>
				<input_output>out</input_output>
				<data_name>atomicIncrementTimeNumOps</data_name>
			</hash_070018649a28926034d8b67867fd064bf31584>
			<hash_070018902fe03a77f910a8eb358feffc6ee809>
				<name>atomicIncrementTimeAvgTime</name>
				<update_rra>on</update_rra>
				<regexp_match></regexp_match>
				<allow_nulls></allow_nulls>
				<type_code></type_code>
				<input_output>out</input_output>
				<data_name>atomicIncrementTimeAvgTime</data_name>
			</hash_070018902fe03a77f910a8eb358feffc6ee809>
			<hash_0700184f99a5285f93c7df9558cba82f3671a8>
				<name>atomicIncrementTimeMinTime</name>
				<update_rra>on</update_rra>
				<regexp_match></regexp_match>
				<allow_nulls></allow_nulls>
				<type_code></type_code>
				<input_output>out</input_output>
				<data_name>atomicIncrementTimeMinTime</data_name>
			</hash_0700184f99a5285f93c7df9558cba82f3671a8>
			<hash_070018ad8edbaeea8ad6969d656b03db033155>
				<name>atomicIncrementTimeMaxTime</name>
				<update_rra>on</update_rra>
				<regexp_match></regexp_match>
				<allow_nulls></allow_nulls>
				<type_code></type_code>
				<input_output>out</input_output>
				<data_name>atomicIncrementTimeMaxTime</data_name>
			</hash_070018ad8edbaeea8ad6969d656b03db033155>
		</fields>
	</hash_030018b6c3fc6020cada88de08ebae65b1efe9>
	<hash_150018c21df5178e5c955013591239eb0afd46>
		<name>Daily (5 Minute Average)</name>
		<x_files_factor>0.5</x_files_factor>
		<steps>1</steps>
		<rows>600</rows>
		<timespan>86400</timespan>
		<cf_items>1|3</cf_items>
	</hash_150018c21df5178e5c955013591239eb0afd46>
	<hash_1500180d9c0af8b8acdc7807943937b3208e29>
		<name>Weekly (30 Minute Average)</name>
		<x_files_factor>0.5</x_files_factor>
		<steps>6</steps>
		<rows>700</rows>
		<timespan>604800</timespan>
		<cf_items>1|3</cf_items>
	</hash_1500180d9c0af8b8acdc7807943937b3208e29>
	<hash_1500186fc2d038fb42950138b0ce3e9874cc60>
		<name>Monthly (2 Hour Average)</name>
		<x_files_factor>0.5</x_files_factor>
		<steps>24</steps>
		<rows>775</rows>
		<timespan>2678400</timespan>
		<cf_items>1|3</cf_items>
	</hash_1500186fc2d038fb42950138b0ce3e9874cc60>
	<hash_150018e36f3adb9f152adfa5dc50fd2b23337e>
		<name>Yearly (1 Day Average)</name>
		<x_files_factor>0.5</x_files_factor>
		<steps>288</steps>
		<rows>797</rows>
		<timespan>33053184</timespan>
		<cf_items>1|3</cf_items>
	</hash_150018e36f3adb9f152adfa5dc50fd2b23337e>
	<hash_060018e9c43831e54eca8069317a2ce8c6f751>
		<name>Normal</name>
		<gprint_text>%8.2lf %s</gprint_text>
	</hash_060018e9c43831e54eca8069317a2ce8c6f751>
</cacti>
